timelapse_maker/__init__.py
timelapse_maker/cli.py
timelapse_maker/core.py
timelapse_maker-0.1.6.dist-info/METADATA
timelapse_maker-0.1.6.dist-info/WHEEL
timelapse_maker-0.1.6.dist-info/entry_points.txt
timelapse_maker-0.1.6.dist-info/RECORD
